degiroasync/__init__.py
degiroasync/py.typed
degiroasync/api/__init__.py
degiroasync/api/orders.py
degiroasync/api/product.py
degiroasync/api/session.py
degiroasync/core/__init__.py
degiroasync/core/constants.py
degiroasync/core/core.py
degiroasync/core/exceptions.py
degiroasync/core/helpers.py
degiroasync/core/py.typed
degiroasync/webapi/__init__.py
degiroasync/webapi/login.py
degiroasync/webapi/orders.py
degiroasync/webapi/product.py
tests/__init__.py
tests/integration_login.py
tests/test_core.py
tests/test_degiroapi.py
tests/test_degirowebapi.py
tests/test_setup.py
degiroasync-0.22.0.dist-info/LICENSE
degiroasync-0.22.0.dist-info/METADATA
degiroasync-0.22.0.dist-info/WHEEL
degiroasync-0.22.0.dist-info/top_level.txt
degiroasync-0.22.0.dist-info/RECORD
