Metadata-Version: 2.1
Name: degiroasync
Version: 0.22.0
Summary: A Python asynchronous library for Degiro trading service.
Home-page: https://github.com/OhMajesticLama/degiroasync
Author-email: ohmajesticlama@gmail.com
Project-URL: Documentation, https://ohmajesticlama.github.io/degiroasync/index.html
Classifier: Programming Language :: Python :: 3
Classifier: License :: OSI Approved :: MIT License
Classifier: Operating System :: OS Independent
Classifier: Development Status :: 4 - Beta
Classifier: Topic :: Software Development :: Libraries :: Python Modules
Classifier: Intended Audience :: Developers
Requires-Python: >=3.8
License-File: LICENSE
Requires-Dist: httpx <1.0,>=0.21.3
Requires-Dist: jsonloader <1.0,>=0.8.1
Requires-Dist: asyncstdlib <4.0,>=3.10.3
Requires-Dist: more-itertools <9,>=8.12.0
Provides-Extra: dev
Requires-Dist: pytest >=7.0.1 ; extra == 'dev'
Requires-Dist: coverage >=6.3 ; extra == 'dev'
Requires-Dist: pandas <3.0,>=2.0.3 ; extra == 'dev'
Requires-Dist: flake8 >=4.0.1 ; extra == 'dev'
Requires-Dist: mypy >=0.931 ; extra == 'dev'
Requires-Dist: build >=0.7.0 ; extra == 'dev'
Requires-Dist: twine >=3.8.0 ; extra == 'dev'
Requires-Dist: sphinx >=4.4.0 ; extra == 'dev'
Requires-Dist: sphinx-rtd-theme >=1.0.0 ; extra == 'dev'
Requires-Dist: myst-parser >=0.17.0 ; extra == 'dev'
Requires-Dist: ipython ; extra == 'dev'
Requires-Dist: ipdb ; extra == 'dev'
